{
	"name": "DS_COPY_DEL",
	"properties": {
		"linkedServiceName": {
			"referenceName": "LS_COPY_DEL",
			"type": "LinkedServiceReference"
		},
		"annotations": [],
		"type": "DelimitedText",
		"typeProperties": {
			"location": {
				"type": "AzureBlobStorageLocation",
				"container": "input120326"
			},
			"columnDelimiter": ",",
			"escapeChar": "\\",
			"firstRowAsHeader": true,
			"quoteChar": "\""
		},
		"schema": [
			{
				"name": "SIC_Code",
				"type": "String"
			},
			{
				"name": "Description",
				"type": "String"
			}
		]
	}
}