{
	"$schema": "http://schema.management.azure.com/schemas/2015-01-01/deploymentTemplate.json#",
	"contentVersion": "1.0.0.0",
	"parameters": {
		"factoryName": {
			"type": "string",
			"metadata": "Data Factory name",
			"defaultValue": "adfnewsqladls"
		},
		"AzureDataLakeStorage1_accountKey": {
			"type": "secureString",
			"metadata": "Secure string for 'accountKey' of 'AzureDataLakeStorage1'"
		},
		"AzureDataLakeStorage2_accountKey": {
			"type": "secureString",
			"metadata": "Secure string for 'accountKey' of 'AzureDataLakeStorage2'"
		},
		"DS7_BLOB_SQL_CSV_connectionString": {
			"type": "secureString",
			"metadata": "Secure string for 'connectionString' of 'DS7_BLOB_SQL_CSV'"
		},
		"DS_PASTE_DEL_accountKey": {
			"type": "secureString",
			"metadata": "Secure string for 'accountKey' of 'DS_PASTE_DEL'"
		},
		"LS7_ADLS_CSV_OUTPUT1_connectionString": {
			"type": "secureString",
			"metadata": "Secure string for 'connectionString' of 'LS7_ADLS_CSV_OUTPUT1'"
		},
		"LS_ADLS_PARQUET_NEW_accountKey": {
			"type": "secureString",
			"metadata": "Secure string for 'accountKey' of 'LS_ADLS_PARQUET_NEW'"
		},
		"LS_COPY_DEL_connectionString": {
			"type": "secureString",
			"metadata": "Secure string for 'connectionString' of 'LS_COPY_DEL'"
		},
		"LS_DEL_connectionString": {
			"type": "secureString",
			"metadata": "Secure string for 'connectionString' of 'LS_DEL'"
		},
		"LS_DEL_CPY_connectionString": {
			"type": "secureString",
			"metadata": "Secure string for 'connectionString' of 'LS_DEL_CPY'"
		},
		"LS_DEL_PASTE_connectionString": {
			"type": "secureString",
			"metadata": "Secure string for 'connectionString' of 'LS_DEL_PASTE'"
		},
		"LS_PARQUET_accountKey": {
			"type": "secureString",
			"metadata": "Secure string for 'accountKey' of 'LS_PARQUET'"
		},
		"AzureDataLakeStorage1_properties_typeProperties_url": {
			"type": "string",
			"defaultValue": "https://adlsthirdtry.dfs.core.windows.net/"
		},
		"AzureDataLakeStorage2_properties_typeProperties_url": {
			"type": "string",
			"defaultValue": "https://adlsthirdtry.dfs.core.windows.net/"
		},
		"DS_PASTE_DEL_properties_typeProperties_url": {
			"type": "string",
			"defaultValue": "https://adlsthirdtry.dfs.core.windows.net/"
		},
		"LS_ADLS_PARQUET_NEW_properties_typeProperties_url": {
			"type": "string",
			"defaultValue": "https://adlsthirdtry.dfs.core.windows.net/"
		},
		"LS_PARQUET_properties_typeProperties_url": {
			"type": "string",
			"defaultValue": "https://adlsthirdtry.dfs.core.windows.net/"
		},
		"RestService1_properties_typeProperties_url": {
			"type": "string",
			"defaultValue": "https://retoolapi.dev/5yDVOt/data"
		}
	},
	"variables": {
		"factoryId": "[concat('Microsoft.DataFactory/factories/', parameters('factoryName'))]"
	},
	"resources": [
		{
			"name": "[concat(parameters('factoryName'), '/AzureDataLakeStorage1')]",
			"type": "Microsoft.DataFactory/factories/linkedServices",
			"apiVersion": "2018-06-01",
			"properties": {
				"annotations": [],
				"type": "AzureBlobFS",
				"typeProperties": {
					"url": "[parameters('AzureDataLakeStorage1_properties_typeProperties_url')]",
					"accountKey": {
						"type": "SecureString",
						"value": "[parameters('AzureDataLakeStorage1_accountKey')]"
					}
				}
			},
			"dependsOn": []
		},
		{
			"name": "[concat(parameters('factoryName'), '/AzureDataLakeStorage2')]",
			"type": "Microsoft.DataFactory/factories/linkedServices",
			"apiVersion": "2018-06-01",
			"properties": {
				"annotations": [],
				"type": "AzureBlobFS",
				"typeProperties": {
					"url": "[parameters('AzureDataLakeStorage2_properties_typeProperties_url')]",
					"accountKey": {
						"type": "SecureString",
						"value": "[parameters('AzureDataLakeStorage2_accountKey')]"
					}
				}
			},
			"dependsOn": []
		},
		{
			"name": "[concat(parameters('factoryName'), '/DS7_BLOB_SQL_CSV')]",
			"type": "Microsoft.DataFactory/factories/linkedServices",
			"apiVersion": "2018-06-01",
			"properties": {
				"annotations": [],
				"type": "AzureBlobStorage",
				"typeProperties": {
					"connectionString": "[parameters('DS7_BLOB_SQL_CSV_connectionString')]"
				}
			},
			"dependsOn": []
		},
		{
			"name": "[concat(parameters('factoryName'), '/DS_PASTE_DEL')]",
			"type": "Microsoft.DataFactory/factories/linkedServices",
			"apiVersion": "2018-06-01",
			"properties": {
				"annotations": [],
				"type": "AzureBlobFS",
				"typeProperties": {
					"url": "[parameters('DS_PASTE_DEL_properties_typeProperties_url')]",
					"accountKey": {
						"type": "SecureString",
						"value": "[parameters('DS_PASTE_DEL_accountKey')]"
					}
				}
			},
			"dependsOn": []
		},
		{
			"name": "[concat(parameters('factoryName'), '/LS7_ADLS_CSV_OUTPUT1')]",
			"type": "Microsoft.DataFactory/factories/linkedServices",
			"apiVersion": "2018-06-01",
			"properties": {
				"annotations": [],
				"type": "AzureBlobStorage",
				"typeProperties": {
					"connectionString": "[parameters('LS7_ADLS_CSV_OUTPUT1_connectionString')]"
				}
			},
			"dependsOn": []
		},
		{
			"name": "[concat(parameters('factoryName'), '/LS_ADLS_PARQUET_NEW')]",
			"type": "Microsoft.DataFactory/factories/linkedServices",
			"apiVersion": "2018-06-01",
			"properties": {
				"annotations": [],
				"type": "AzureBlobFS",
				"typeProperties": {
					"url": "[parameters('LS_ADLS_PARQUET_NEW_properties_typeProperties_url')]",
					"accountKey": {
						"type": "SecureString",
						"value": "[parameters('LS_ADLS_PARQUET_NEW_accountKey')]"
					}
				}
			},
			"dependsOn": []
		},
		{
			"name": "[concat(parameters('factoryName'), '/LS_COPY_DEL')]",
			"type": "Microsoft.DataFactory/factories/linkedServices",
			"apiVersion": "2018-06-01",
			"properties": {
				"annotations": [],
				"type": "AzureBlobStorage",
				"typeProperties": {
					"connectionString": "[parameters('LS_COPY_DEL_connectionString')]"
				}
			},
			"dependsOn": []
		},
		{
			"name": "[concat(parameters('factoryName'), '/LS_DEL')]",
			"type": "Microsoft.DataFactory/factories/linkedServices",
			"apiVersion": "2018-06-01",
			"properties": {
				"annotations": [],
				"type": "AzureBlobStorage",
				"typeProperties": {
					"connectionString": "[parameters('LS_DEL_connectionString')]"
				}
			},
			"dependsOn": []
		},
		{
			"name": "[concat(parameters('factoryName'), '/LS_DEL_CPY')]",
			"type": "Microsoft.DataFactory/factories/linkedServices",
			"apiVersion": "2018-06-01",
			"properties": {
				"annotations": [],
				"type": "AzureBlobStorage",
				"typeProperties": {
					"connectionString": "[parameters('LS_DEL_CPY_connectionString')]"
				}
			},
			"dependsOn": []
		},
		{
			"name": "[concat(parameters('factoryName'), '/LS_DEL_PASTE')]",
			"type": "Microsoft.DataFactory/factories/linkedServices",
			"apiVersion": "2018-06-01",
			"properties": {
				"annotations": [],
				"type": "AzureBlobStorage",
				"typeProperties": {
					"connectionString": "[parameters('LS_DEL_PASTE_connectionString')]"
				}
			},
			"dependsOn": []
		},
		{
			"name": "[concat(parameters('factoryName'), '/LS_PARQUET')]",
			"type": "Microsoft.DataFactory/factories/linkedServices",
			"apiVersion": "2018-06-01",
			"properties": {
				"annotations": [],
				"type": "AzureBlobFS",
				"typeProperties": {
					"url": "[parameters('LS_PARQUET_properties_typeProperties_url')]",
					"accountKey": {
						"type": "SecureString",
						"value": "[parameters('LS_PARQUET_accountKey')]"
					}
				}
			},
			"dependsOn": []
		},
		{
			"name": "[concat(parameters('factoryName'), '/RestService1')]",
			"type": "Microsoft.DataFactory/factories/linkedServices",
			"apiVersion": "2018-06-01",
			"properties": {
				"annotations": [],
				"type": "RestService",
				"typeProperties": {
					"url": "[parameters('RestService1_properties_typeProperties_url')]",
					"enableServerCertificateValidation": true,
					"authenticationType": "Anonymous"
				}
			},
			"dependsOn": []
		},
		{
			"name": "[concat(parameters('factoryName'), '/integrationRuntime1')]",
			"type": "Microsoft.DataFactory/factories/integrationRuntimes",
			"apiVersion": "2018-06-01",
			"properties": {
				"type": "SelfHosted",
				"typeProperties": {}
			},
			"dependsOn": []
		},
		{
			"name": "[concat(parameters('factoryName'), '/DS7_ADLS_CSV_OUTPUT')]",
			"type": "Microsoft.DataFactory/factories/datasets",
			"apiVersion": "2018-06-01",
			"properties": {
				"linkedServiceName": {
					"referenceName": "LS7_ADLS_CSV_OUTPUT1",
					"type": "LinkedServiceReference"
				},
				"annotations": [],
				"type": "DelimitedText",
				"typeProperties": {
					"location": {
						"type": "AzureBlobStorageLocation",
						"container": "outputadlscsv"
					},
					"columnDelimiter": ",",
					"escapeChar": "\\",
					"firstRowAsHeader": true,
					"quoteChar": "\""
				},
				"schema": []
			},
			"dependsOn": [
				"[concat(variables('factoryId'), '/linkedServices/LS7_ADLS_CSV_OUTPUT1')]"
			]
		},
		{
			"name": "[concat(parameters('factoryName'), '/DS_ADLS_PARQUET_NEW')]",
			"type": "Microsoft.DataFactory/factories/datasets",
			"apiVersion": "2018-06-01",
			"properties": {
				"linkedServiceName": {
					"referenceName": "LS_ADLS_PARQUET_NEW",
					"type": "LinkedServiceReference"
				},
				"annotations": [],
				"type": "Parquet",
				"typeProperties": {
					"location": {
						"type": "AzureBlobFSLocation",
						"fileSystem": "outputnew"
					},
					"compressionCodec": "snappy"
				},
				"schema": []
			},
			"dependsOn": [
				"[concat(variables('factoryId'), '/linkedServices/LS_ADLS_PARQUET_NEW')]"
			]
		},
		{
			"name": "[concat(parameters('factoryName'), '/DS_COPY_DEL')]",
			"type": "Microsoft.DataFactory/factories/datasets",
			"apiVersion": "2018-06-01",
			"properties": {
				"linkedServiceName": {
					"referenceName": "LS_COPY_DEL",
					"type": "LinkedServiceReference"
				},
				"annotations": [],
				"type": "DelimitedText",
				"typeProperties": {
					"location": {
						"type": "AzureBlobStorageLocation",
						"container": "input120326"
					},
					"columnDelimiter": ",",
					"escapeChar": "\\",
					"firstRowAsHeader": true,
					"quoteChar": "\""
				},
				"schema": [
					{
						"name": "SIC_Code",
						"type": "String"
					},
					{
						"name": "Description",
						"type": "String"
					}
				]
			},
			"dependsOn": [
				"[concat(variables('factoryId'), '/linkedServices/LS_COPY_DEL')]"
			]
		},
		{
			"name": "[concat(parameters('factoryName'), '/DS_DEL')]",
			"type": "Microsoft.DataFactory/factories/datasets",
			"apiVersion": "2018-06-01",
			"properties": {
				"linkedServiceName": {
					"referenceName": "LS_DEL_CPY",
					"type": "LinkedServiceReference"
				},
				"annotations": [],
				"type": "Binary",
				"typeProperties": {
					"location": {
						"type": "AzureBlobStorageLocation",
						"container": "input120326"
					}
				}
			},
			"dependsOn": [
				"[concat(variables('factoryId'), '/linkedServices/LS_DEL_CPY')]"
			]
		},
		{
			"name": "[concat(parameters('factoryName'), '/DS_PASTE_DEL')]",
			"type": "Microsoft.DataFactory/factories/datasets",
			"apiVersion": "2018-06-01",
			"properties": {
				"linkedServiceName": {
					"referenceName": "DS_PASTE_DEL",
					"type": "LinkedServiceReference"
				},
				"annotations": [],
				"type": "Parquet",
				"typeProperties": {
					"location": {
						"type": "AzureBlobFSLocation",
						"fileSystem": "output120326"
					},
					"compressionCodec": "snappy"
				},
				"schema": []
			},
			"dependsOn": [
				"[concat(variables('factoryId'), '/linkedServices/DS_PASTE_DEL')]"
			]
		},
		{
			"name": "[concat(parameters('factoryName'), '/Parquet1')]",
			"type": "Microsoft.DataFactory/factories/datasets",
			"apiVersion": "2018-06-01",
			"properties": {
				"linkedServiceName": {
					"referenceName": "AzureDataLakeStorage2",
					"type": "LinkedServiceReference"
				},
				"annotations": [],
				"type": "Parquet",
				"typeProperties": {
					"location": {
						"type": "AzureBlobFSLocation",
						"fileSystem": "outputnew"
					},
					"compressionCodec": "snappy"
				},
				"schema": [
					{
						"name": "CustomerID",
						"type": "INT32"
					},
					{
						"name": "NameStyle",
						"type": "BOOLEAN"
					},
					{
						"name": "Title",
						"type": "UTF8"
					},
					{
						"name": "FirstName",
						"type": "UTF8"
					},
					{
						"name": "MiddleName",
						"type": "UTF8"
					},
					{
						"name": "LastName",
						"type": "UTF8"
					},
					{
						"name": "Suffix",
						"type": "UTF8"
					},
					{
						"name": "CompanyName",
						"type": "UTF8"
					},
					{
						"name": "SalesPerson",
						"type": "UTF8"
					},
					{
						"name": "EmailAddress",
						"type": "UTF8"
					},
					{
						"name": "Phone",
						"type": "UTF8"
					},
					{
						"name": "PasswordHash",
						"type": "UTF8"
					},
					{
						"name": "PasswordSalt",
						"type": "UTF8"
					},
					{
						"name": "rowguid",
						"type": "UTF8"
					},
					{
						"name": "ModifiedDate",
						"type": "INT96"
					}
				]
			},
			"dependsOn": [
				"[concat(variables('factoryId'), '/linkedServices/AzureDataLakeStorage2')]"
			]
		},
		{
			"name": "[concat(parameters('factoryName'), '/RestResource1')]",
			"type": "Microsoft.DataFactory/factories/datasets",
			"apiVersion": "2018-06-01",
			"properties": {
				"linkedServiceName": {
					"referenceName": "RestService1",
					"type": "LinkedServiceReference"
				},
				"annotations": [],
				"type": "RestResource",
				"typeProperties": {},
				"schema": []
			},
			"dependsOn": [
				"[concat(variables('factoryId'), '/linkedServices/RestService1')]"
			]
		}
	]
}